{"call_started": "17:47:50.831294", "called_end": "17:48:46.321060", "phone_number": "01692511030", "disposition": "XFER", "states": [{"state_name": "S_HELLO", "playing": ["hello.wav"], "transcript": {"helping_trans": "hi", "transcript": " hi"}, "predicted_class": {"res": "greetings", "method": "b"}}, {"state_name": "S_INTRO", "playing": ["./sounds/merri/intro/intro_pitch_q.wav"], "transcript": {"helping_trans": "i'm already having to him", "transcript": " i am already having everything."}, "predicted_class": {"res": "already", "method": "b"}}, {"state_name": "S_Already", "playing": ["Already_Rebuttal.wav"], "transcript": {"helping_trans": "i'll provide", "transcript": " okay, go ahead."}, "predicted_class": {"res": "interested", "method": "b"}}, {"state_name": "S_TRANSFER", "playing": ["transfer.wav"], "transcript": {"helping_trans": "", "transcript": ""}}]}