{"call_started": "18:58:56.612479", "called_end": "18:59:45.231521", "phone_number": "02711988710", "disposition": "XFER", "states": [{"state_name": "S_HELLO", "playing": ["hello.wav"], "transcript": {"helping_trans": "hello hi there", "transcript": ""}, "predicted_class": {"res": "greetings", "method": "b"}}, {"state_name": "S_INTRO", "playing": ["./sounds/merri/intro/intro_pitch_q.wav"], "transcript": {"helping_trans": "say her medicare part a and part me", "transcript": " i have medicare part a and part b."}, "predicted_class": {"res": "affirmation", "method": "b"}}, {"state_name": "S_TRANSFER", "playing": ["transfer.wav"], "transcript": {"helping_trans": "i can show", "transcript": " okay, sure."}, "predicted_class": {"res": "interested", "method": "b"}}]}